Metadata-Version: 2.1
Name: sagemaker-studio-image-build
Version: 0.6.0
Summary: Build Docker Images in Amazon SageMaker Studio using AWS CodeBuild
Home-page: https://github.com/aws-samples/sagemaker-studio-image-build-cli
Author: Amazon Web Services
License: MIT-0
Platform: UNKNOWN
Classifier: Intended Audience :: Developers
Classifier: Intended Audience :: Science/Research
Classifier: Programming Language :: Python
Classifier: Programming Language :: Python :: 3
Classifier: Programming Language :: Python :: 3.6
Classifier: Programming Language :: Python :: 3.7
Requires-Python: >=3.6
Provides-Extra: dev
